rp2paths/DotHandler.py
rp2paths/DotMaker.py
rp2paths/DotStyle.py
rp2paths/EFMHandler.py
rp2paths/IDsHandler.py
rp2paths/ImgHandler.py
rp2paths/ImgMaker.py
rp2paths/PathFilter.py
rp2paths/RP2paths.py
rp2paths/Scope.py
rp2paths/__init__.py
rp2paths/__main__.py
rp2paths/rp2erxn.py
rp2paths-1.5.1.dist-info/LICENSE.txt
rp2paths-1.5.1.dist-info/METADATA
rp2paths-1.5.1.dist-info/WHEEL
rp2paths-1.5.1.dist-info/top_level.txt
rp2paths-1.5.1.dist-info/RECORD
