Metadata-Version: 2.1
Name: rp2paths
Version: 1.5.1
Summary: 'retropath2.0 to pathways'
Home-page: https://github.com/brsynth/rp2paths
Author: 'thomas duigou'
Author-email: thomas.duigou@inrae.fr
License: MIT
Platform: UNKNOWN
Classifier: Programming Language :: Python :: 3
Classifier: License :: OSI Approved :: MIT License
Classifier: Operating System :: OS Independent
Requires-Python: >=3.5
Requires-Dist: pandas
Requires-Dist: pydotplus
Requires-Dist: graphviz
Requires-Dist: lxml
